BioDisco/__init__.py
BioDisco/agents_auto_background.py
BioDisco/agents_evidence.py
BioDisco/utils/__init__.py
BioDisco/utils/libraries.py
BioDisco/utils/llm_config.py
BioDisco/utils/log_utils.py
BioDisco/utils/neo4j_query.py
BioDisco/utils/pubmed_query.py
biodisco-0.1.0.dist-info/licenses/LICENSE
biodisco-0.1.0.dist-info/METADATA
biodisco-0.1.0.dist-info/WHEEL
biodisco-0.1.0.dist-info/top_level.txt
biodisco-0.1.0.dist-info/RECORD
