Metadata-Version: 2.4
Name: biodisco
Version: 0.1.0
Summary: AI-powered Biomedical Discovery Agent System
Home-page: https://github.com/yujingke/BioDisco
Author: BioDisco Team
Project-URL: Bug Reports, https://github.com/yujingke/BioDisco/issues
Project-URL: Source, https://github.com/yujingke/BioDisco
Keywords: biomedical,AI,agents,hypothesis generation,literature mining,knowledge graph
Classifier: Development Status :: 4 - Beta
Classifier: Intended Audience :: Science/Research
Classifier: License :: OSI Approved :: MIT License
Classifier: Programming Language :: Python :: 3.11
Requires-Python: >=3.11
License-File: LICENSE
Requires-Dist: langroid>=0.58.0
Requires-Dist: transformers>=4.53.0
Requires-Dist: neo4j>=5.28.0
Requires-Dist: autogen>=0.9.6
Requires-Dist: faiss-cpu>=1.11.0
Requires-Dist: sentence-transformers>=5.0.0
Requires-Dist: python-dotenv>=1.0.0
Dynamic: author
Dynamic: classifier
Dynamic: description
Dynamic: description-content-type
Dynamic: home-page
Dynamic: keywords
Dynamic: license-file
Dynamic: project-url
Dynamic: requires-dist
Dynamic: requires-python
Dynamic: summary
